hypercortex/__init__.py
hypercortex/py.typed
hypercortex/agents/__init__.py
hypercortex/agents/bank_agent.py
hypercortex/agents/hello_world.py
hypercortex/utils/__init__.py
hypercortex/utils/helpers.py
hypercortex-0.1.0.dist-info/METADATA
hypercortex-0.1.0.dist-info/WHEEL
hypercortex-0.1.0.dist-info/RECORD
