Metadata-Version: 2.4
Name: hypercortex
Version: 0.1.0
Summary: AI Agent for healthcare fintech
Author-email: Chris Dare <engineering@chrisdare.me>
Requires-Python: >=3.10
Requires-Dist: fastapi>=0.115.6
Requires-Dist: jupyterlab>=4.3.4
Requires-Dist: pydantic-ai>=0.0.17
